{
    "$schema": "http://w3id.org/opentecr/schema/data/v1.0.0",
    "@id": "http://w3id.org/opentecr/data/c7ca5ae0-c27e-41fe-ac7b-6d90a031c4c9/v1.0.0",
    "curator": {
        "orcid": "https://orcid.org/0000-0002-7288-535X",
        "name": "Andrew Philip Freiburger"
    },
    "CuratedMeasurement": {
        "reference": {
            "pmid": " ",
            "doi": " ",
            "url": "",
            "title": "",
            "authors": "",
            "year": "",
            "journal": "",
            "tecrdb_id": "43KRE/EGG_1162",
            "tecrdb_string": "Krebs H.A.; Eggleston L.V.; Biochim. J.; 37 334 (1943)."
        },
        "representative_reaction": {
            "name": "aconitate hydratase",
            "KEGG": "kegg:C00311 = kegg:C00158",
            "CID": " ",
            "stoichiometry": {
                "reactants": {
                    "isocitrate(aq) ": 1
                },
                "products": {
                    " citrate(aq)": 1
                }
            }
        },
        "equilibriumConstant": "14.4",
        "hydrogenPotential": "6.8",
        "magnesiumPotential": "",
        "temperature": "298.15",
        "ionicStrength": " "
    },
    "_comment": "What is the following content?",
    "ActualInformation": {
        "md5_of_pdf": "",
        "doi_of_zenodo_archive": "",
        "download_url_of_zenodo_archive": "",
        "comments": ""
    }
}