{
    "$schema": "http://w3id.org/opentecr/schema/data/v1.0.0",
    "@id": "http://w3id.org/opentecr/data/c7ca5ae0-c27e-41fe-ac7b-6d90a031c4c9/v1.0.0",
    "curator": {
        "orcid": "https://orcid.org/0000-0002-7288-535X",
        "name": "Andrew Philip Freiburger"
    },
    "CuratedMeasurement": {
        "reference": {
            "pmid": " ",
            "doi": " ",
            "url": "",
            "title": "",
            "authors": "",
            "year": "",
            "journal": "",
            "tecrdb_id": "65ONO/HIR_902",
            "tecrdb_string": "Ono S.; Hiromi K.; Takahashi K.; J. Biochem. (Tokyo); 57 799 (1965)."
        },
        "representative_reaction": {
            "name": "glucan 1,4-a-glucosidase",
            "KEGG": " ",
            "CID": " ",
            "stoichiometry": {
                "reactants": {
                    "phenyl \u00ce\u00b1-maltoside(aq)": 1,
                    "H2O(l) ": 1
                },
                "products": {
                    " phenyl \u00ce\u00b1-D-glucopyranoside(aq)": 1,
                    "D-glucose(aq)": 1
                }
            }
        },
        "equilibriumConstant": " ",
        "hydrogenPotential": "4.5",
        "magnesiumPotential": "",
        "temperature": "298.15",
        "ionicStrength": " "
    },
    "_comment": "What is the following content?",
    "ActualInformation": {
        "md5_of_pdf": "",
        "doi_of_zenodo_archive": "",
        "download_url_of_zenodo_archive": "",
        "comments": ""
    }
}