{
    "$schema": "http://w3id.org/opentecr/schema/data/v1.0.0",
    "@id": "http://w3id.org/opentecr/data/c7ca5ae0-c27e-41fe-ac7b-6d90a031c4c9/v1.0.0",
    "curator": {
        "orcid": "https://orcid.org/0000-0002-7288-535X",
        "name": "Andrew Philip Freiburger"
    },
    "CuratedMeasurement": {
        "reference": {
            "pmid": "4344229.0",
            "doi": " ",
            "url": "",
            "title": "",
            "authors": "",
            "year": "",
            "journal": "",
            "tecrdb_id": "72BAK/JEN_290",
            "tecrdb_string": "Baker J.J.; Jeng I.; Barker H.A.; J. Biol. Chem.; 247 7724 (1972)."
        },
        "representative_reaction": {
            "name": "L-erythro-3,5-diaminohexanoate dehydrogenase",
            "KEGG": "kegg:C01186 + kegg:C00003 + kegg:C00001 = kegg:C03656 + kegg:C00004 + kegg:C00014",
            "CID": "CHB_15377 + CHB_15846 + CHB_21282 = CHB_16134 + CHB_16908 + CHB_27713",
            "stoichiometry": {
                "reactants": {
                    "L-erythro-3,5-diaminohexanoate(aq)": 1,
                    "NAD(aq)": 1,
                    "H2O(l) ": 1
                },
                "products": {
                    " (S)-5-amino-3-oxohexanoate(aq)": 1,
                    "NADH(aq)": 1,
                    "ammonia(aq)": 1
                }
            }
        },
        "equilibriumConstant": "0.004",
        "hydrogenPotential": "7.0",
        "magnesiumPotential": "",
        "temperature": "299.15",
        "ionicStrength": " "
    },
    "_comment": "What is the following content?",
    "ActualInformation": {
        "md5_of_pdf": "",
        "doi_of_zenodo_archive": "",
        "download_url_of_zenodo_archive": "",
        "comments": ""
    }
}