{
    "$schema": "http://w3id.org/opentecr/schema/data/v1.0.0",
    "@id": "http://w3id.org/opentecr/data/c7ca5ae0-c27e-41fe-ac7b-6d90a031c4c9/v1.0.0",
    "curator": {
        "orcid": "https://orcid.org/0000-0002-7288-535X",
        "name": "Andrew Philip Freiburger"
    },
    "CuratedMeasurement": {
        "reference": {
            "pmid": " ",
            "doi": " ",
            "url": "",
            "title": "",
            "authors": "",
            "year": "",
            "journal": "",
            "tecrdb_id": "92LOR/TRA_741",
            "tecrdb_string": "Lortie R.; Trani M.; Ergan F.; Prog. Biotechnol.; 8 519 (1992)"
        },
        "representative_reaction": {
            "name": "triacylglycerol lipase",
            "KEGG": " ",
            "CID": "CHB_15377 + PBC_5497163 = CHB_16196 + PBC_5497164",
            "stoichiometry": {
                "reactants": {
                    "triolein(aq)": 1,
                    "H2O(l) ": 1
                },
                "products": {
                    " oleic acid(aq)": 1,
                    "diolein(aq)": 1
                }
            }
        },
        "equilibriumConstant": "0.083",
        "hydrogenPotential": " ",
        "magnesiumPotential": "",
        "temperature": "333.15",
        "ionicStrength": " "
    },
    "_comment": "What is the following content?",
    "ActualInformation": {
        "md5_of_pdf": "",
        "doi_of_zenodo_archive": "",
        "download_url_of_zenodo_archive": "",
        "comments": ""
    }
}